odoo_rpc_client/__init__.py
odoo_rpc_client/client.py
odoo_rpc_client/exceptions.py
odoo_rpc_client/plugin.py
odoo_rpc_client/utils.py
odoo_rpc_client/version.py
odoo_rpc_client/connection/__init__.py
odoo_rpc_client/connection/connection.py
odoo_rpc_client/connection/jsonrpc.py
odoo_rpc_client/connection/xmlrpc.py
odoo_rpc_client/orm/__init__.py
odoo_rpc_client/orm/cache.py
odoo_rpc_client/orm/object.py
odoo_rpc_client/orm/record.py
odoo_rpc_client/orm/service.py
odoo_rpc_client/plugins/__init__.py
odoo_rpc_client/plugins/external_ids.py
odoo_rpc_client/plugins/module_utils.py
odoo_rpc_client/service/__init__.py
odoo_rpc_client/service/db.py
odoo_rpc_client/service/object.py
odoo_rpc_client/service/report.py
odoo_rpc_client/service/service.py
odoo_rpc_client/tests/__init__.py
odoo_rpc_client/tests/all.py
odoo_rpc_client/tests/test_client.py
odoo_rpc_client/tests/test_connection.py
odoo_rpc_client/tests/test_db.py
odoo_rpc_client/tests/test_orm.py
odoo_rpc_client/tests/test_plugins.py
odoo_rpc_client/tests/test_service_report.py
odoo_rpc_client/tests/test_utils.py
odoo_rpc_client-1.2.0.dist-info/LICENSE
odoo_rpc_client-1.2.0.dist-info/METADATA
odoo_rpc_client-1.2.0.dist-info/WHEEL
odoo_rpc_client-1.2.0.dist-info/top_level.txt
odoo_rpc_client-1.2.0.dist-info/RECORD
