Metadata-Version: 2.1
Name: odoo_rpc_client
Version: 1.2.0
Summary: Odoo library for RPC
Home-page: https://gitlab.com/katyukha/odoo-rpc-client
Author: Dmytro Katyukha
Author-email: dmytro.katyukha@gmail.com
License: MPL 2.0
Keywords: odoo,odoo-rpc,rpc,xmlrpc,xml-rpc,json-rpc,jsonrpc,odoo-client,openerp
Classifier: Development Status :: 5 - Production/Stable
Classifier: Intended Audience :: Developers
Classifier: License :: OSI Approved :: Mozilla Public License 2.0 (MPL 2.0)
Classifier: Programming Language :: Python
Classifier: Programming Language :: Python :: 2
Classifier: Programming Language :: Python :: 2.7
Classifier: Programming Language :: Python :: 3
Classifier: Programming Language :: Python :: 3.3
Classifier: Programming Language :: Python :: 3.4
Classifier: Programming Language :: Python :: 3.5
Classifier: Programming Language :: Python :: 3.6
Classifier: Programming Language :: Python :: 3.7
Classifier: Programming Language :: Python :: Implementation :: CPython
Classifier: Topic :: Utilities
Classifier: Topic :: Software Development :: Libraries
Classifier: Topic :: Software Development :: Libraries :: Python Modules
Provides-Extra: all
License-File: LICENSE
